seCronTab/__init__.py
seCronTab/_version.py
seCronTab/cron_field.py
seCronTab/cronconfig.py
seCronTab/crontab.py
seCronTab/utils.py
secrontab-2025.1.0rc1.dist-info/METADATA
secrontab-2025.1.0rc1.dist-info/WHEEL
secrontab-2025.1.0rc1.dist-info/top_level.txt
secrontab-2025.1.0rc1.dist-info/RECORD
