Metadata-Version: 2.2
Name: secrontab
Version: 2025.1.0rc1
Summary: CronTab Scheduler
Author-email: Cybernetic Innovations <github@cyberneticinnovations.com>
License: MIT License
Classifier: License :: OSI Approved :: MIT License
Requires-Python: >=3.10
Requires-Dist: seversion
